quiz_questions/__init__.py
quiz_questions/core.py
quiz_questions/questions.py
aptitudetest-0.1.0.dist-info/LICENSE
aptitudetest-0.1.0.dist-info/METADATA
aptitudetest-0.1.0.dist-info/WHEEL
aptitudetest-0.1.0.dist-info/top_level.txt
aptitudetest-0.1.0.dist-info/RECORD
